ministudio/__init__.py
ministudio/api.py
ministudio/audio.py
ministudio/cli.py
ministudio/compiler.py
ministudio/config.py
ministudio/core.py
ministudio/gradio_app.py
ministudio/interfaces.py
ministudio/orchestrator.py
ministudio/s3_utils.py
ministudio/state.py
ministudio/utils.py
ministudio-0.1.1.dist-info/METADATA
ministudio-0.1.1.dist-info/WHEEL
ministudio-0.1.1.dist-info/entry_points.txt
ministudio-0.1.1.dist-info/top_level.txt
ministudio-0.1.1.dist-info/RECORD
