Metadata-Version: 2.4
Name: ministudio
Version: 0.1.1
Summary: Model-Agnostic AI Video Generation Framework
Author-email: Ministudio Team <team@ministudio.ai>
License-Expression: MIT
Classifier: Development Status :: 3 - Alpha
Classifier: Intended Audience :: Developers
Classifier: Programming Language :: Python :: 3
Classifier: Programming Language :: Python :: 3.8
Classifier: Programming Language :: Python :: 3.9
Classifier: Programming Language :: Python :: 3.10
Classifier: Programming Language :: Python :: 3.11
Classifier: Programming Language :: Python :: 3.12
Classifier: Topic :: Multimedia :: Video
Requires-Python: >=3.8
Requires-Dist: fastapi
Requires-Dist: uvicorn[standard]
Requires-Dist: gradio
Requires-Dist: moviepy
Requires-Dist: google-cloud-texttospeech
Requires-Dist: boto3
Requires-Dist: pillow
Requires-Dist: numpy
Provides-Extra: vertex-ai
Requires-Dist: google-genai; extra == "vertex-ai"
Provides-Extra: openai
Requires-Dist: openai; extra == "openai"
Requires-Dist: requests; extra == "openai"
Provides-Extra: all
Requires-Dist: google-genai; extra == "all"
Requires-Dist: openai; extra == "all"
Requires-Dist: requests; extra == "all"
